MockCraftPython/__init__.py
MockCraftPython-0.1.dist-info/METADATA
MockCraftPython-0.1.dist-info/WHEEL
MockCraftPython-0.1.dist-info/top_level.txt
MockCraftPython-0.1.dist-info/RECORD
